{
  "version": "7",
  "dialect": "postgresql",
  "entries": [
    {
      "idx": 0,
      "version": "7",
      "when": 1777998625742,
      "tag": "0000_volatile_riptide",
      "breakpoints": true
    },
    {
      "idx": 1,
      "version": "7",
      "when": 1779526500288,
      "tag": "0001_empty_korath",
      "breakpoints": true
    },
    {
      "idx": 2,
      "version": "7",
      "when": 1779629174983,
      "tag": "0002_slippery_ken_ellis",
      "breakpoints": true
    },
    {
      "idx": 3,
      "version": "7",
      "when": 1779633050679,
      "tag": "0003_real_mysterio",
      "breakpoints": true
    },
    {
      "idx": 4,
      "version": "7",
      "when": 1780144953837,
      "tag": "0004_spooky_bedlam",
      "breakpoints": true
    },
    {
      "idx": 5,
      "version": "7",
      "when": 1781961304373,
      "tag": "0005_nebulous_malcolm_colcord",
      "breakpoints": true
    }
  ]
}